const/__init__.py
const/color.py
const/maths.py
const/physics.py
constlib/__init__.py
constlib/color.py
constlib/maths.py
constlib/physics.py
constlib-0.1.0.dist-info/LICENSE
constlib-0.1.0.dist-info/METADATA
constlib-0.1.0.dist-info/WHEEL
constlib-0.1.0.dist-info/top_level.txt
constlib-0.1.0.dist-info/RECORD
